{
    "project_name": "Angel-ML-angel",
    "violation_id": "105",
    "information": {
        "violations": [
            {
                "line": "6",
                "severity": "error",
                "message": "Line is longer than 100 characters (found 102).",
                "source": "com.puppycrawl.tools.checkstyle.checks.sizes.LineLengthCheck"
            }
        ]
    },
    "source_code": " * Copyright (C) 2017-2018 THL A29 Limited, a Tencent company. All rights reserved.\n *\n * Licensed under the Apache License, Version 2.0 (the \"License\"); you may not use this file except in\n * compliance with the License. You may obtain a copy of the License at\n *\n * https://opensource.org/licenses/Apache-2.0",
    "results": [
        {
            "tool": "styler",
            "violations": [
                {
                    "line": "6",
                    "severity": "error",
                    "message": "Line is longer than 100 characters (found 102).",
                    "source": "com.puppycrawl.tools.checkstyle.checks.sizes.LineLengthCheck"
                }
            ],
            "diff": "",
            "diff_size": 0
        },
        {
            "tool": "checkstyle_idea",
            "violations": [
                {
                    "line": "6",
                    "severity": "error",
                    "message": "Line is longer than 100 characters (found 102).",
                    "source": "com.puppycrawl.tools.checkstyle.checks.sizes.LineLengthCheck"
                }
            ],
            "diff": "diff --git a/home/fernanda/mnt/fernanda/git-styler/styler/src/experiments/projects/Angel-ML-angel/violations/105/GBTTree.java b/home/fernanda/mnt/fernanda/git-styler/styler/src/experiments/projects/Angel-ML-angel/checkstyle_idea/105/GBTTree.java\nindex 85b541dcfdd..4b0a55a8832 100644\n--- a/home/fernanda/mnt/fernanda/git-styler/styler/src/experiments/projects/Angel-ML-angel/violations/105/GBTTree.java\n+++ b/home/fernanda/mnt/fernanda/git-styler/styler/src/experiments/projects/Angel-ML-angel/checkstyle_idea/105/GBTTree.java\n@@ -23,9 +23,9 @@ import com.tencent.angel.spark.ml.tree.tree.param.GBDTParam;\n \n public class GBTTree extends Tree<GBDTParam, GBTNode> {\n \n-  public GBTTree(GBDTParam param) {\n-    super(param);\n-    GBTNode root = new GBTNode(0, null, param.numClass);\n-    this.nodes.put(0, root);\n-  }\n+    public GBTTree(GBDTParam param) {\n+        super(param);\n+        GBTNode root = new GBTNode(0, null, param.numClass);\n+        this.nodes.put(0, root);\n+    }\n }\n",
            "diff_size": 5
        },
        {
            "tool": "naturalize",
            "violations": [
                {
                    "line": "6",
                    "severity": "error",
                    "message": "Line is longer than 100 characters (found 102).",
                    "source": "com.puppycrawl.tools.checkstyle.checks.sizes.LineLengthCheck"
                }
            ],
            "diff": "diff --git a/home/fernanda/mnt/fernanda/git-styler/styler/src/experiments/projects/Angel-ML-angel/violations/105/GBTTree.java b/home/fernanda/mnt/fernanda/git-styler/styler/src/experiments/projects/Angel-ML-angel/naturalize/105/GBTTree.java\nindex 85b541dcfdd..3a4113c8dae 100644\n--- a/home/fernanda/mnt/fernanda/git-styler/styler/src/experiments/projects/Angel-ML-angel/violations/105/GBTTree.java\n+++ b/home/fernanda/mnt/fernanda/git-styler/styler/src/experiments/projects/Angel-ML-angel/naturalize/105/GBTTree.java\n@@ -15,7 +15,6 @@\n  *\n  */\n \n-\n package com.tencent.angel.spark.ml.tree.gbdt.tree;\n \n import com.tencent.angel.spark.ml.tree.tree.basic.Tree;\n@@ -28,4 +27,4 @@ public class GBTTree extends Tree<GBDTParam, GBTNode> {\n     GBTNode root = new GBTNode(0, null, param.numClass);\n     this.nodes.put(0, root);\n   }\n-}\n+}\n\\ No newline at end of file\n",
            "diff_size": 2
        },
        {
            "tool": "codebuff",
            "violations": [
                {
                    "line": "6",
                    "severity": "error",
                    "message": "Line is longer than 100 characters (found 102).",
                    "source": "com.puppycrawl.tools.checkstyle.checks.sizes.LineLengthCheck"
                }
            ],
            "diff": "diff --git a/home/fernanda/mnt/fernanda/git-styler/styler/src/experiments/projects/Angel-ML-angel/violations/105/GBTTree.java b/home/fernanda/mnt/fernanda/git-styler/styler/src/experiments/projects/Angel-ML-angel/codebuff/105/GBTTree.java\nindex 85b541dcfdd..8190679375e 100644\n--- a/home/fernanda/mnt/fernanda/git-styler/styler/src/experiments/projects/Angel-ML-angel/violations/105/GBTTree.java\n+++ b/home/fernanda/mnt/fernanda/git-styler/styler/src/experiments/projects/Angel-ML-angel/codebuff/105/GBTTree.java\n@@ -28,4 +28,4 @@ public class GBTTree extends Tree<GBDTParam, GBTNode> {\n     GBTNode root = new GBTNode(0, null, param.numClass);\n     this.nodes.put(0, root);\n   }\n-}\n+}\n\\ No newline at end of file\n",
            "diff_size": 1
        },
        {
            "tool": "styler_random",
            "violations": [
                {
                    "line": "6",
                    "severity": "error",
                    "message": "Line is longer than 100 characters (found 102).",
                    "source": "com.puppycrawl.tools.checkstyle.checks.sizes.LineLengthCheck"
                }
            ],
            "diff": "",
            "diff_size": 0
        },
        {
            "tool": "styler_three_grams",
            "violations": [
                {
                    "line": "6",
                    "severity": "error",
                    "message": "Line is longer than 100 characters (found 102).",
                    "source": "com.puppycrawl.tools.checkstyle.checks.sizes.LineLengthCheck"
                }
            ],
            "diff": "",
            "diff_size": 0
        }
    ],
    "repaired_by": [],
    "not_repaired_by": [
        "styler",
        "checkstyle_idea",
        "naturalize",
        "codebuff",
        "styler_random",
        "styler_three_grams"
    ]
}