{
    "project_name": "apache-servicecomb-java-chassis",
    "violation_id": "351",
    "information": {
        "violations": [
            {
                "line": "113",
                "severity": "warning",
                "message": "Line is longer than 120 characters (found 122).",
                "source": "com.puppycrawl.tools.checkstyle.checks.sizes.LineLengthCheck"
            }
        ]
    },
    "source_code": "\n  @SuppressWarnings(\"unchecked\")\n  public static <SWAGGER_PARAMETER, ANNOTATION> ParameterProcessor<SWAGGER_PARAMETER, ANNOTATION> findParameterProcessors(\n      Type type) {\n    return (ParameterProcessor<SWAGGER_PARAMETER, ANNOTATION>) parameterProcessors.get(type);\n  }",
    "results": [
        {
            "tool": "styler",
            "violations": [
                {
                    "line": "113",
                    "severity": "warning",
                    "message": "Line is longer than 120 characters (found 140).",
                    "source": "com.puppycrawl.tools.checkstyle.checks.sizes.LineLengthCheck"
                },
                {
                    "line": "113",
                    "column": "18",
                    "severity": "warning",
                    "message": "'<' is followed by whitespace.",
                    "source": "com.puppycrawl.tools.checkstyle.checks.whitespace.GenericWhitespaceCheck"
                },
                {
                    "line": "113",
                    "column": "37",
                    "severity": "warning",
                    "message": "',' is not followed by whitespace.",
                    "source": "com.puppycrawl.tools.checkstyle.checks.whitespace.WhitespaceAfterCheck"
                },
                {
                    "line": "113",
                    "column": "47",
                    "severity": "warning",
                    "message": "'>' is preceded with whitespace.",
                    "source": "com.puppycrawl.tools.checkstyle.checks.whitespace.GenericWhitespaceCheck"
                },
                {
                    "line": "113",
                    "column": "69",
                    "severity": "warning",
                    "message": "'<' is followed by whitespace.",
                    "source": "com.puppycrawl.tools.checkstyle.checks.whitespace.GenericWhitespaceCheck"
                },
                {
                    "line": "113",
                    "column": "87",
                    "severity": "warning",
                    "message": "',' is preceded with whitespace.",
                    "source": "com.puppycrawl.tools.checkstyle.checks.whitespace.NoWhitespaceBeforeCheck"
                },
                {
                    "line": "113",
                    "column": "100",
                    "severity": "warning",
                    "message": "'>' is preceded with whitespace.",
                    "source": "com.puppycrawl.tools.checkstyle.checks.whitespace.GenericWhitespaceCheck"
                },
                {
                    "line": "113",
                    "column": "127",
                    "severity": "warning",
                    "message": "'(' is preceded with whitespace.",
                    "source": "com.puppycrawl.tools.checkstyle.checks.whitespace.MethodParamPadCheck"
                },
                {
                    "line": "113",
                    "column": "128",
                    "severity": "warning",
                    "message": "'(' is followed by whitespace.",
                    "source": "com.puppycrawl.tools.checkstyle.checks.whitespace.ParenPadCheck"
                }
            ],
            "diff": "diff --git a/home/fernanda/mnt/fernanda/git-styler/styler/src/experiments/projects/apache-servicecomb-java-chassis/violations/351/SwaggerGeneratorUtils.java b/home/fernanda/mnt/fernanda/git-styler/styler/src/./experiments/projects/apache-servicecomb-java-chassis/styler/05_predictions/final/files-repaired/351/SwaggerGeneratorUtils.java\nindex 4d8e1361bae..d7a4757f112 100644\n--- a/home/fernanda/mnt/fernanda/git-styler/styler/src/experiments/projects/apache-servicecomb-java-chassis/violations/351/SwaggerGeneratorUtils.java\n+++ b/home/fernanda/mnt/fernanda/git-styler/styler/src/./experiments/projects/apache-servicecomb-java-chassis/styler/05_predictions/final/files-repaired/351/SwaggerGeneratorUtils.java\n@@ -110,8 +110,7 @@ public final class SwaggerGeneratorUtils {\n   }\n \n   @SuppressWarnings(\"unchecked\")\n-  public static <SWAGGER_PARAMETER, ANNOTATION> ParameterProcessor<SWAGGER_PARAMETER, ANNOTATION> findParameterProcessors(\n-      Type type) {\n+  public static < SWAGGER_PARAMETER,ANNOTATION > ParameterProcessor< SWAGGER_PARAMETER , ANNOTATION > findParameterProcessors ( Type type) {\n     return (ParameterProcessor<SWAGGER_PARAMETER, ANNOTATION>) parameterProcessors.get(type);\n   }\n \n",
            "diff_size": 2
        },
        {
            "tool": "checkstyle_idea",
            "violations": [
                {
                    "line": "114",
                    "severity": "warning",
                    "message": "Line is longer than 120 characters (found 122).",
                    "source": "com.puppycrawl.tools.checkstyle.checks.sizes.LineLengthCheck"
                }
            ],
            "diff": "diff --git a/home/fernanda/mnt/fernanda/git-styler/styler/src/experiments/projects/apache-servicecomb-java-chassis/violations/351/SwaggerGeneratorUtils.java b/home/fernanda/mnt/fernanda/git-styler/styler/src/experiments/projects/apache-servicecomb-java-chassis/checkstyle_idea/351/SwaggerGeneratorUtils.java\nindex 4d8e1361bae..0f9ef14ca31 100644\n--- a/home/fernanda/mnt/fernanda/git-styler/styler/src/experiments/projects/apache-servicecomb-java-chassis/violations/351/SwaggerGeneratorUtils.java\n+++ b/home/fernanda/mnt/fernanda/git-styler/styler/src/experiments/projects/apache-servicecomb-java-chassis/checkstyle_idea/351/SwaggerGeneratorUtils.java\n@@ -14,6 +14,7 @@\n  * See the License for the specific language governing permissions and\n  * limitations under the License.\n  */\n+\n package org.apache.servicecomb.swagger.generator;\n \n import java.lang.annotation.Annotation;\n@@ -210,7 +211,8 @@ public final class SwaggerGeneratorUtils {\n   }\n \n   public static List<Annotation> collectParameterAnnotations(Annotation[] parameterAnnotations,\n-      Map<String, List<Annotation>> methodAnnotationMap, String parameterName) {\n+                                                             Map<String, List<Annotation>> methodAnnotationMap,\n+                                                             String parameterName) {\n     List<Annotation> methodAnnotations = methodAnnotationMap.remove(parameterName);\n     if (methodAnnotations == null) {\n       methodAnnotations = Collections.emptyList();\n",
            "diff_size": 3
        },
        {
            "tool": "naturalize",
            "violations": [
                {
                    "line": "113",
                    "severity": "warning",
                    "message": "Line is longer than 120 characters (found 122).",
                    "source": "com.puppycrawl.tools.checkstyle.checks.sizes.LineLengthCheck"
                }
            ],
            "diff": "diff --git a/home/fernanda/mnt/fernanda/git-styler/styler/src/experiments/projects/apache-servicecomb-java-chassis/violations/351/SwaggerGeneratorUtils.java b/home/fernanda/mnt/fernanda/git-styler/styler/src/experiments/projects/apache-servicecomb-java-chassis/naturalize/351/SwaggerGeneratorUtils.java\nindex 4d8e1361bae..90d2da10c2e 100644\n--- a/home/fernanda/mnt/fernanda/git-styler/styler/src/experiments/projects/apache-servicecomb-java-chassis/violations/351/SwaggerGeneratorUtils.java\n+++ b/home/fernanda/mnt/fernanda/git-styler/styler/src/experiments/projects/apache-servicecomb-java-chassis/naturalize/351/SwaggerGeneratorUtils.java\n@@ -112,7 +112,7 @@ public final class SwaggerGeneratorUtils {\n   @SuppressWarnings(\"unchecked\")\n   public static <SWAGGER_PARAMETER, ANNOTATION> ParameterProcessor<SWAGGER_PARAMETER, ANNOTATION> findParameterProcessors(\n       Type type) {\n-    return (ParameterProcessor<SWAGGER_PARAMETER, ANNOTATION>) parameterProcessors.get(type);\n+  return (ParameterProcessor<SWAGGER_PARAMETER, ANNOTATION>) parameterProcessors.get(type);\n   }\n \n   public static ResponseTypeProcessor findResponseTypeProcessor(Type type) {\n@@ -179,7 +179,7 @@ public final class SwaggerGeneratorUtils {\n     }\n \n     String msg = String.format(\"parameter name is not present, method=%s:%s\\n\"\n-            + \"solution:\\n\"\n+    + \"solution:\\n\"\n             + \"  change pom.xml, add compiler argument: -parameters, for example:\\n\"\n             + \"    <plugin>\\n\"\n             + \"      <groupId>org.apache.maven.plugins</groupId>\\n\"\n@@ -245,4 +245,4 @@ public final class SwaggerGeneratorUtils {\n \n     return processor.getHttpParameterType(parameterAnnotation);\n   }\n-}\n+}\n\\ No newline at end of file\n",
            "diff_size": 3
        },
        {
            "tool": "codebuff",
            "violations": [
                {
                    "line": "48",
                    "severity": "warning",
                    "message": "Line is longer than 120 characters (found 154).",
                    "source": "com.puppycrawl.tools.checkstyle.checks.sizes.LineLengthCheck"
                },
                {
                    "line": "49",
                    "severity": "warning",
                    "message": "Line is longer than 120 characters (found 139).",
                    "source": "com.puppycrawl.tools.checkstyle.checks.sizes.LineLengthCheck"
                },
                {
                    "line": "63",
                    "severity": "warning",
                    "message": "Line is longer than 120 characters (found 122).",
                    "source": "com.puppycrawl.tools.checkstyle.checks.sizes.LineLengthCheck"
                },
                {
                    "line": "71",
                    "severity": "warning",
                    "message": "Line is longer than 120 characters (found 124).",
                    "source": "com.puppycrawl.tools.checkstyle.checks.sizes.LineLengthCheck"
                },
                {
                    "line": "113",
                    "severity": "warning",
                    "message": "Line is longer than 120 characters (found 134).",
                    "source": "com.puppycrawl.tools.checkstyle.checks.sizes.LineLengthCheck"
                },
                {
                    "line": "186",
                    "severity": "warning",
                    "message": "Line is longer than 120 characters (found 505).",
                    "source": "com.puppycrawl.tools.checkstyle.checks.sizes.LineLengthCheck"
                },
                {
                    "line": "206",
                    "severity": "warning",
                    "message": "Line is longer than 120 characters (found 170).",
                    "source": "com.puppycrawl.tools.checkstyle.checks.sizes.LineLengthCheck"
                }
            ],
            "diff": "diff --git a/home/fernanda/mnt/fernanda/git-styler/styler/src/experiments/projects/apache-servicecomb-java-chassis/violations/351/SwaggerGeneratorUtils.java b/home/fernanda/mnt/fernanda/git-styler/styler/src/experiments/projects/apache-servicecomb-java-chassis/codebuff/351/SwaggerGeneratorUtils.java\nindex 4d8e1361bae..dbc30e990b8 100644\n--- a/home/fernanda/mnt/fernanda/git-styler/styler/src/experiments/projects/apache-servicecomb-java-chassis/violations/351/SwaggerGeneratorUtils.java\n+++ b/home/fernanda/mnt/fernanda/git-styler/styler/src/experiments/projects/apache-servicecomb-java-chassis/codebuff/351/SwaggerGeneratorUtils.java\n@@ -28,17 +28,14 @@ import java.util.List;\n import java.util.Map;\n import java.util.Set;\n import java.util.stream.Collectors;\n-\n import org.apache.commons.lang3.StringUtils;\n import org.apache.servicecomb.foundation.common.utils.SPIServiceUtils;\n import org.apache.servicecomb.swagger.generator.core.model.HttpParameterType;\n import org.apache.servicecomb.swagger.generator.core.processor.response.DefaultResponseTypeProcessor;\n import org.slf4j.Logger;\n import org.slf4j.LoggerFactory;\n-\n import com.fasterxml.jackson.databind.Module;\n import com.fasterxml.jackson.databind.introspect.BeanPropertyDefinition;\n-\n import io.swagger.models.parameters.Parameter;\n import io.swagger.util.Json;\n \n@@ -46,9 +43,10 @@ public final class SwaggerGeneratorUtils {\n   private static final Logger LOGGER = LoggerFactory.getLogger(SwaggerGeneratorUtils.class);\n \n   // all static fields load from SPI and stateless\n+\n   private static Set<Type> contextTypes = SPIServiceUtils.getOrLoadSortedService(SwaggerContextRegister.class).stream()\n-      .map(SwaggerContextRegister::getContextType)\n-      .collect(Collectors.toSet());\n+                                                                                                              .map(SwaggerContextRegister::getContextType)\n+                                                                                                              .collect(Collectors.toSet());\n \n   private static Map<Type, ClassAnnotationProcessor<?>> classAnnotationProcessors = new HashMap<>();\n \n@@ -62,33 +60,35 @@ public final class SwaggerGeneratorUtils {\n \n   static {\n     // low order value has high priority\n-    for (ClassAnnotationProcessor<?> processor : SPIServiceUtils\n-        .getOrLoadSortedService(ClassAnnotationProcessor.class)) {\n+    for (ClassAnnotationProcessor<?> processor : SPIServiceUtils.getOrLoadSortedService(ClassAnnotationProcessor.class)) {\n       if (classAnnotationProcessors.putIfAbsent(processor.getProcessType(), processor) != null) {\n         LOGGER.info(\"ignore duplicated ClassAnnotationProcessor, type={}, processor={}.\",\n-            processor.getProcessType().getTypeName(), processor.getClass().getName());\n+processor.getProcessType().getTypeName(),\n+processor.getClass().getName());\n       }\n     }\n \n-    for (MethodAnnotationProcessor<?> processor : SPIServiceUtils\n-        .getOrLoadSortedService(MethodAnnotationProcessor.class)) {\n+    for (MethodAnnotationProcessor<?> processor : SPIServiceUtils.getOrLoadSortedService(MethodAnnotationProcessor.class)) {\n       if (methodAnnotationProcessors.putIfAbsent(processor.getProcessType(), processor) != null) {\n         LOGGER.info(\"ignore duplicated MethodAnnotationProcessor, type={}, processor={}.\",\n-            processor.getProcessType().getTypeName(), processor.getClass().getName());\n+processor.getProcessType().getTypeName(),\n+processor.getClass().getName());\n       }\n     }\n \n     for (ParameterProcessor<?, ?> processor : SPIServiceUtils.getOrLoadSortedService(ParameterProcessor.class)) {\n       if (parameterProcessors.putIfAbsent(processor.getProcessType(), processor) != null) {\n         LOGGER.info(\"ignore duplicated ParameterProcessor, type={}, processor={}.\",\n-            processor.getProcessType().getTypeName(), processor.getClass().getName());\n+processor.getProcessType().getTypeName(),\n+processor.getClass().getName());\n       }\n     }\n \n     for (ResponseTypeProcessor processor : SPIServiceUtils.getOrLoadSortedService(ResponseTypeProcessor.class)) {\n       if (responseTypeProcessors.putIfAbsent(processor.getProcessType(), processor) != null) {\n         LOGGER.info(\"ignore duplicated ResponseTypeProcessor, type={}, processor={}.\",\n-            processor.getProcessType().getTypeName(), processor.getClass().getName());\n+processor.getProcessType().getTypeName(),\n+processor.getClass().getName());\n       }\n     }\n \n@@ -110,8 +110,7 @@ public final class SwaggerGeneratorUtils {\n   }\n \n   @SuppressWarnings(\"unchecked\")\n-  public static <SWAGGER_PARAMETER, ANNOTATION> ParameterProcessor<SWAGGER_PARAMETER, ANNOTATION> findParameterProcessors(\n-      Type type) {\n+  public static <SWAGGER_PARAMETER, ANNOTATION> ParameterProcessor<SWAGGER_PARAMETER, ANNOTATION> findParameterProcessors(Type type) {\n     return (ParameterProcessor<SWAGGER_PARAMETER, ANNOTATION>) parameterProcessors.get(type);\n   }\n \n@@ -124,7 +123,6 @@ public final class SwaggerGeneratorUtils {\n     if (type instanceof ParameterizedType) {\n       return responseTypeProcessors.getOrDefault(((ParameterizedType) type).getRawType(), defaultResponseTypeProcessor);\n     }\n-\n     return defaultResponseTypeProcessor;\n   }\n \n@@ -135,20 +133,26 @@ public final class SwaggerGeneratorUtils {\n   public static Annotation[] collectAnnotations(BeanPropertyDefinition propertyDefinition) {\n     List<Annotation> annotations = new ArrayList<>();\n     if (propertyDefinition.getField() != null) {\n-      Collections.addAll(annotations, propertyDefinition.getField().getAnnotated().getAnnotations());\n+      Collections.addAll(annotations, propertyDefinition.getField().getAnnotated()\n+                                                                   .getAnnotations());\n     }\n+\n     if (propertyDefinition.getGetter() != null) {\n-      Collections.addAll(annotations, propertyDefinition.getGetter().getAnnotated().getAnnotations());\n+      Collections.addAll(annotations, propertyDefinition.getGetter().getAnnotated()\n+                                                                    .getAnnotations());\n     }\n+\n     if (propertyDefinition.getSetter() != null) {\n-      Collections.addAll(annotations, propertyDefinition.getSetter().getAnnotated().getAnnotations());\n+      Collections.addAll(annotations, propertyDefinition.getSetter().getAnnotated()\n+                                                                    .getAnnotations());\n     }\n     return annotations.toArray(new Annotation[annotations.size()]);\n   }\n \n   public static String collectParameterName(java.lang.reflect.Parameter methodParameter) {\n-    return collectParameterName(methodParameter.getDeclaringExecutable(), methodParameter.getAnnotations(),\n-        methodParameter.isNamePresent() ? methodParameter.getName() : null);\n+    return collectParameterName(methodParameter.getDeclaringExecutable(),\n+methodParameter.getAnnotations(),\n+methodParameter.isNamePresent() ? methodParameter.getName() : null);\n   }\n \n   public static String collectParameterName(Method method, BeanPropertyDefinition propertyDefinition) {\n@@ -174,21 +178,12 @@ public final class SwaggerGeneratorUtils {\n \n     // 2.use signature name\n     // ensure present parameter name\n+\n     if (StringUtils.isNotEmpty(defaultName)) {\n       return defaultName;\n     }\n \n-    String msg = String.format(\"parameter name is not present, method=%s:%s\\n\"\n-            + \"solution:\\n\"\n-            + \"  change pom.xml, add compiler argument: -parameters, for example:\\n\"\n-            + \"    <plugin>\\n\"\n-            + \"      <groupId>org.apache.maven.plugins</groupId>\\n\"\n-            + \"      <artifactId>maven-compiler-plugin</artifactId>\\n\"\n-            + \"      <configuration>\\n\"\n-            + \"        <compilerArgument>-parameters</compilerArgument>\\n\"\n-            + \"      </configuration>\\n\"\n-            + \"    </plugin>\",\n-        executable.getDeclaringClass().getName(), executable.getName());\n+    String msg = String.format(\"parameter name is not present, method=%s:%s\\n\" + \"solution:\\n\" + \"  change pom.xml, add compiler argument: -parameters, for example:\\n\" + \"    <plugin>\\n\" + \"      <groupId>org.apache.maven.plugins</groupId>\\n\" + \"      <artifactId>maven-compiler-plugin</artifactId>\\n\" + \"      <configuration>\\n\" + \"        <compilerArgument>-parameters</compilerArgument>\\n\" + \"      </configuration>\\n\" + \"    </plugin>\", executable.getDeclaringClass().getName(), executable.getName());\n     throw new IllegalStateException(msg);\n   }\n \n@@ -205,12 +200,10 @@ public final class SwaggerGeneratorUtils {\n         genericType = type;\n       }\n     }\n-\n     return genericType != null ? genericType : defaultType;\n   }\n \n-  public static List<Annotation> collectParameterAnnotations(Annotation[] parameterAnnotations,\n-      Map<String, List<Annotation>> methodAnnotationMap, String parameterName) {\n+  public static List<Annotation> collectParameterAnnotations(Annotation[] parameterAnnotations, Map<String, List<Annotation>> methodAnnotationMap, String parameterName) {\n     List<Annotation> methodAnnotations = methodAnnotationMap.remove(parameterName);\n     if (methodAnnotations == null) {\n       methodAnnotations = Collections.emptyList();\n@@ -219,7 +212,6 @@ public final class SwaggerGeneratorUtils {\n     List<Annotation> annotations = new ArrayList<>();\n     Collections.addAll(annotations, parameterAnnotations);\n     annotations.addAll(methodAnnotations);\n-\n     return annotations;\n   }\n \n@@ -242,7 +234,6 @@ public final class SwaggerGeneratorUtils {\n     if (processor == null) {\n       return null;\n     }\n-\n     return processor.getHttpParameterType(parameterAnnotation);\n   }\n-}\n+}\n\\ No newline at end of file\n",
            "diff_size": 50
        },
        {
            "tool": "styler_random",
            "violations": [
                {
                    "line": "113",
                    "severity": "warning",
                    "message": "Line is longer than 120 characters (found 140).",
                    "source": "com.puppycrawl.tools.checkstyle.checks.sizes.LineLengthCheck"
                },
                {
                    "line": "113",
                    "column": "18",
                    "severity": "warning",
                    "message": "'<' is followed by whitespace.",
                    "source": "com.puppycrawl.tools.checkstyle.checks.whitespace.GenericWhitespaceCheck"
                },
                {
                    "line": "113",
                    "column": "37",
                    "severity": "warning",
                    "message": "',' is not followed by whitespace.",
                    "source": "com.puppycrawl.tools.checkstyle.checks.whitespace.WhitespaceAfterCheck"
                },
                {
                    "line": "113",
                    "column": "47",
                    "severity": "warning",
                    "message": "'>' is preceded with whitespace.",
                    "source": "com.puppycrawl.tools.checkstyle.checks.whitespace.GenericWhitespaceCheck"
                },
                {
                    "line": "113",
                    "column": "69",
                    "severity": "warning",
                    "message": "'<' is followed by whitespace.",
                    "source": "com.puppycrawl.tools.checkstyle.checks.whitespace.GenericWhitespaceCheck"
                },
                {
                    "line": "113",
                    "column": "87",
                    "severity": "warning",
                    "message": "',' is preceded with whitespace.",
                    "source": "com.puppycrawl.tools.checkstyle.checks.whitespace.NoWhitespaceBeforeCheck"
                },
                {
                    "line": "113",
                    "column": "100",
                    "severity": "warning",
                    "message": "'>' is preceded with whitespace.",
                    "source": "com.puppycrawl.tools.checkstyle.checks.whitespace.GenericWhitespaceCheck"
                },
                {
                    "line": "113",
                    "column": "127",
                    "severity": "warning",
                    "message": "'(' is preceded with whitespace.",
                    "source": "com.puppycrawl.tools.checkstyle.checks.whitespace.MethodParamPadCheck"
                },
                {
                    "line": "113",
                    "column": "128",
                    "severity": "warning",
                    "message": "'(' is followed by whitespace.",
                    "source": "com.puppycrawl.tools.checkstyle.checks.whitespace.ParenPadCheck"
                }
            ],
            "diff": "diff --git a/home/fernanda/mnt/fernanda/git-styler/styler/src/experiments/projects/apache-servicecomb-java-chassis/violations/351/SwaggerGeneratorUtils.java b/home/fernanda/mnt/fernanda/git-styler/styler/src/experiments/projects/apache-servicecomb-java-chassis/styler/05_predictions/random/files-repaired/351/SwaggerGeneratorUtils.java\nindex 4d8e1361bae..d7a4757f112 100644\n--- a/home/fernanda/mnt/fernanda/git-styler/styler/src/experiments/projects/apache-servicecomb-java-chassis/violations/351/SwaggerGeneratorUtils.java\n+++ b/home/fernanda/mnt/fernanda/git-styler/styler/src/experiments/projects/apache-servicecomb-java-chassis/styler/05_predictions/random/files-repaired/351/SwaggerGeneratorUtils.java\n@@ -110,8 +110,7 @@ public final class SwaggerGeneratorUtils {\n   }\n \n   @SuppressWarnings(\"unchecked\")\n-  public static <SWAGGER_PARAMETER, ANNOTATION> ParameterProcessor<SWAGGER_PARAMETER, ANNOTATION> findParameterProcessors(\n-      Type type) {\n+  public static < SWAGGER_PARAMETER,ANNOTATION > ParameterProcessor< SWAGGER_PARAMETER , ANNOTATION > findParameterProcessors ( Type type) {\n     return (ParameterProcessor<SWAGGER_PARAMETER, ANNOTATION>) parameterProcessors.get(type);\n   }\n \n",
            "diff_size": 2
        },
        {
            "tool": "styler_three_grams",
            "violations": null,
            "diff": null
        }
    ],
    "repaired_by": [],
    "not_repaired_by": [
        "styler",
        "checkstyle_idea",
        "naturalize",
        "codebuff",
        "styler_random",
        "styler_three_grams"
    ]
}