{
    "project_name": "neo4j-neo4j",
    "violation_id": "2328",
    "information": {
        "violations": [
            {
                "line": "1",
                "severity": "error",
                "message": "Missing, wrong or duplicated license header",
                "source": "com.puppycrawl.tools.checkstyle.checks.regexp.RegexpSinglelineCheck"
            }
        ]
    },
    "source_code": "/*\n * Copyright (c) 2002-2020 \"Neo4j,\"\n * Neo4j Sweden AB [http://neo4j.com]\n *",
    "results": [
        {
            "tool": "styler",
            "violations": [
                {
                    "line": "1",
                    "severity": "error",
                    "message": "Missing, wrong or duplicated license header",
                    "source": "com.puppycrawl.tools.checkstyle.checks.regexp.RegexpSinglelineCheck"
                }
            ],
            "diff": "",
            "diff_size": 0
        },
        {
            "tool": "checkstyle_idea",
            "violations": [
                {
                    "line": "1",
                    "severity": "error",
                    "message": "Missing, wrong or duplicated license header",
                    "source": "com.puppycrawl.tools.checkstyle.checks.regexp.RegexpSinglelineCheck"
                },
                {
                    "line": "29",
                    "column": "29",
                    "severity": "error",
                    "message": "'(' is not followed by whitespace.",
                    "source": "com.puppycrawl.tools.checkstyle.checks.whitespace.ParenPadCheck"
                },
                {
                    "line": "29",
                    "column": "63",
                    "severity": "error",
                    "message": "')' is not preceded with whitespace.",
                    "source": "com.puppycrawl.tools.checkstyle.checks.whitespace.ParenPadCheck"
                },
                {
                    "line": "43",
                    "column": "12",
                    "severity": "error",
                    "message": "'(' is not followed by whitespace.",
                    "source": "com.puppycrawl.tools.checkstyle.checks.whitespace.ParenPadCheck"
                },
                {
                    "line": "43",
                    "column": "22",
                    "severity": "error",
                    "message": "')' is not preceded with whitespace.",
                    "source": "com.puppycrawl.tools.checkstyle.checks.whitespace.ParenPadCheck"
                },
                {
                    "line": "50",
                    "column": "21",
                    "severity": "error",
                    "message": "'(' is not followed by whitespace.",
                    "source": "com.puppycrawl.tools.checkstyle.checks.whitespace.ParenPadCheck"
                },
                {
                    "line": "50",
                    "column": "28",
                    "severity": "error",
                    "message": "')' is not preceded with whitespace.",
                    "source": "com.puppycrawl.tools.checkstyle.checks.whitespace.ParenPadCheck"
                },
                {
                    "line": "58",
                    "column": "12",
                    "severity": "error",
                    "message": "'(' is not followed by whitespace.",
                    "source": "com.puppycrawl.tools.checkstyle.checks.whitespace.ParenPadCheck"
                },
                {
                    "line": "58",
                    "column": "22",
                    "severity": "error",
                    "message": "')' is not preceded with whitespace.",
                    "source": "com.puppycrawl.tools.checkstyle.checks.whitespace.ParenPadCheck"
                }
            ],
            "diff": "diff --git a/home/fernanda/mnt/fernanda/git-styler/styler/src/experiments/projects/neo4j-neo4j/violations/2328/HeapTrackingStack.java b/home/fernanda/mnt/fernanda/git-styler/styler/src/experiments/projects/neo4j-neo4j/checkstyle_idea/2328/HeapTrackingStack.java\nindex 98c7ed6527e..00d1f98f58a 100644\n--- a/home/fernanda/mnt/fernanda/git-styler/styler/src/experiments/projects/neo4j-neo4j/violations/2328/HeapTrackingStack.java\n+++ b/home/fernanda/mnt/fernanda/git-styler/styler/src/experiments/projects/neo4j-neo4j/checkstyle_idea/2328/HeapTrackingStack.java\n@@ -17,6 +17,7 @@\n  * You should have received a copy of the GNU General Public License\n  * along with this program.  If not, see <http://www.gnu.org/licenses/>.\n  */\n+\n package org.neo4j.collection.trackable;\n \n import java.util.EmptyStackException;\n@@ -25,7 +26,7 @@ public class HeapTrackingStack<T> implements AutoCloseable\n {\n     private final HeapTrackingArrayList<T> delegate;\n \n-    public HeapTrackingStack( HeapTrackingArrayList<T> delegate )\n+    public HeapTrackingStack(HeapTrackingArrayList<T> delegate)\n     {\n         this.delegate = delegate;\n     }\n@@ -39,26 +40,26 @@ public class HeapTrackingStack<T> implements AutoCloseable\n     public T peek()\n     {\n         int size = delegate.size();\n-        if ( size == 0 )\n+        if (size == 0)\n         {\n             throw new EmptyStackException();\n         }\n         return delegate.get(size - 1);\n     }\n \n-    public void push( T item )\n+    public void push(T item)\n     {\n-        delegate.add( item );\n+        delegate.add(item);\n     }\n \n     public T pop()\n     {\n         int size = delegate.size();\n-        if ( size == 0 )\n+        if (size == 0)\n         {\n             throw new EmptyStackException();\n         }\n-        return delegate.remove( size - 1 );\n+        return delegate.remove(size - 1);\n     }\n \n     public int size()\n",
            "diff_size": 7
        },
        {
            "tool": "naturalize",
            "violations": null,
            "diff": null
        },
        {
            "tool": "codebuff",
            "violations": null,
            "diff": null
        },
        {
            "tool": "styler_random",
            "violations": [
                {
                    "line": "1",
                    "severity": "error",
                    "message": "Missing, wrong or duplicated license header",
                    "source": "com.puppycrawl.tools.checkstyle.checks.regexp.RegexpSinglelineCheck"
                }
            ],
            "diff": "",
            "diff_size": 0
        },
        {
            "tool": "styler_three_grams",
            "violations": [
                {
                    "line": "1",
                    "severity": "error",
                    "message": "Missing, wrong or duplicated license header",
                    "source": "com.puppycrawl.tools.checkstyle.checks.regexp.RegexpSinglelineCheck"
                }
            ],
            "diff": "",
            "diff_size": 0
        }
    ],
    "repaired_by": [],
    "not_repaired_by": [
        "styler",
        "checkstyle_idea",
        "naturalize",
        "codebuff",
        "styler_random",
        "styler_three_grams"
    ]
}